{
    "nodes": [
        {"id": "Node0", "label":"Projects", "group": 1},
        {"id": "Node1", "label":"Projects", "group": 1},
        {"id": "Node2", "label":"Projects", "group": 1},
        {"id": "Node3", "label":"Projects", "group": 1},
        {"id": "Node4", "label":"Projects", "group": 1},
        {"id": "Node5", "label":"Projects", "group": 1},
        {"id": "Node6", "label":"Projects", "group": 1},
        {"id": "Node7", "label":"Projects", "group": 1},
        {"id": "Node8", "label":"Projects", "group": 1},
        {"id": "Node9", "label":"Projects", "group": 1},
        {"id": "Node10", "label":"Projects", "group": 1},
        {"id": "Node11", "label":"Projects", "group": 1},
        {"id": "Node12", "label":"Projects", "group": 1},
        {"id": "Node13", "label":"Projects", "group": 1},
        {"id": "Node14", "label":"Projects", "group": 1},
        {"id": "Node15", "label":"Projects", "group": 1},
        {"id": "Node16", "label":"Projects", "group": 1},
        {"id": "Node17", "label":"Projects", "group": 1},
        {"id": "Node18", "label":"Projects", "group": 1},
        {"id": "Node19", "label":"Projects", "group": 1},
        {"id": "Node20", "label":"Projects", "group": 1},
        {"id": "Node21", "label":"Projects", "group": 1},
        {"id": "Node22", "label":"Projects", "group": 1},
        {"id": "Node23", "label":"Projects", "group": 1},
        {"id": "Node24", "label":"Projects", "group": 1},
        {"id": "Node25", "label":"Projects", "group": 1},
        {"id": "Node26", "label":"Projects", "group": 1}, 
        {"id": "Node27", "label":"Projects", "group": 1},
        {"id": "Node28", "label":"Projects", "group": 1},
        {"id": "Node29", "label":"Projects", "group": 1},
        {"id": "Node30", "label":"Projects", "group": 1},
        {"id": "Node31", "label":"Projects", "group": 1},
        {"id": "Node32", "label":"Projects", "group": 1},
        {"id": "Node33", "label":"Projects", "group": 1},
        {"id": "Node34", "label":"Projects", "group": 1},
        {"id": "Node35", "label":"Projects", "group": 1},
        {"id": "Node36", "label":"Projects", "group": 1},
        {"id": "Node37", "label":"Projects", "group": 1},
        {"id": "Node38", "label":"Projects", "group": 1},
        {"id": "Node39", "label":"Projects", "group": 1},
        {"id": "Node40", "label":"Projects", "group": 1},
        {"id": "Node41", "label":"Projects", "group": 1},
        {"id": "Node42", "label":"Projects", "group": 1},
        {"id": "Node43", "label":"Projects", "group": 1},
        {"id": "Node44", "label":"Projects", "group": 1},
        {"id": "Node45", "label":"Projects", "group": 1},
        {"id": "Node46", "label":"Projects", "group": 1},
        {"id": "Node47", "label":"Projects", "group": 1},
        {"id": "Node48", "label":"Projects", "group": 1},
        {"id": "Node49", "label":"Projects", "group": 1},
        {"id": "Node50", "label":"Projects", "group": 1},
        {"id": "Node51", "label":"Projects", "group": 1},
        {"id": "Node52", "label":"Projects", "group": 1},
        {"id": "Node53", "label":"Projects", "group": 1}, 
        {"id": "Node54", "label":"Projects", "group": 1},
        {"id": "Node55", "label":"Projects", "group": 1},
        {"id": "Node56", "label":"Projects", "group": 1},
        {"id": "Node57", "label":"Projects", "group": 1},
        {"id": "Node58", "label":"Projects", "group": 1},
        {"id": "Node59", "label":"Projects", "group": 1},
        {"id": "Node60", "label":"Projects", "group": 1},
        {"id": "Node61", "label":"Projects", "group": 1},
        {"id": "Node62", "label":"Projects", "group": 1},
        {"id": "Node63", "label":"Projects", "group": 1},
        {"id": "Node64", "label":"Projects", "group": 1},
        {"id": "Node65", "label":"Projects", "group": 1},
        {"id": "Node66", "label":"Projects", "group": 1},
        {"id": "Node67", "label":"Projects", "group": 1},
        {"id": "Node68", "label":"Projects", "group": 1},
        {"id": "Node69", "label":"Projects", "group": 1},
        {"id": "Node70", "label":"Projects", "group": 1},
        {"id": "Node71", "label":"Projects", "group": 1},
        {"id": "Node72", "label":"Projects", "group": 1},
        {"id": "Node73", "label":"Projects", "group": 1},
        {"id": "Node74", "label":"Projects", "group": 1},
        {"id": "Node75", "label":"Projects", "group": 1},
        {"id": "Node76", "label":"Projects", "group": 1},
        {"id": "Node77", "label":"Projects", "group": 1},
        {"id": "Node78", "label":"Projects", "group": 1},
        {"id": "Node79", "label":"Projects", "group": 1},
        {"id": "Node80", "label":"Projects", "group": 1}, 
        {"id": "Node81", "label":"Projects", "group": 1},
        {"id": "Node82", "label":"Projects", "group": 1},
        {"id": "Node83", "label":"Projects", "group": 1},
        {"id": "Node84", "label":"Projects", "group": 1},
        {"id": "Node85", "label":"Projects", "group": 1},
        {"id": "Node86", "label":"Projects", "group": 1},
        {"id": "Node87", "label":"Projects", "group": 1},
        {"id": "Node88", "label":"Projects", "group": 1},
        {"id": "Node89", "label":"Projects", "group": 1},
        {"id": "Node90", "label":"Projects", "group": 1},
        {"id": "Node91", "label":"Projects", "group": 1},
        {"id": "Node92", "label":"Projects", "group": 1},
        {"id": "Node93", "label":"Projects", "group": 1},
        {"id": "Node94", "label":"Projects", "group": 1},
        {"id": "Node95", "label":"Projects", "group": 1},
        {"id": "Node96", "label":"Projects", "group": 1},
        {"id": "Node97", "label":"Projects", "group": 1},
        {"id": "Node98", "label":"Projects", "group": 1},
        {"id": "Node99", "label":"Projects", "group": 1},
        {"id": "Node100", "label":"Projects", "group": 1},
        {"id": "Node101", "label":"Projects", "group": 1},
        {"id": "Node102", "label":"Projects", "group": 1},
        {"id": "Node103", "label":"Projects", "group": 1},
        {"id": "Node104", "label":"Projects", "group": 1},
        {"id": "Node105", "label":"Projects", "group": 1},
        {"id": "Node106", "label":"Projects", "group": 1},
        {"id": "Node107", "label":"Projects", "group": 1}, 
        {"id": "Node108", "label":"Projects", "group": 1},
        {"id": "Node109", "label":"Projects", "group": 1},
        {"id": "Node110", "label":"Projects", "group": 1},
        {"id": "Node111", "label":"Projects", "group": 1},
        {"id": "Node112", "label":"Projects", "group": 1},
        {"id": "Node113", "label":"Projects", "group": 1},
        {"id": "Node114", "label":"Projects", "group": 1},
        {"id": "Node115", "label":"Projects", "group": 1},
        {"id": "Node116", "label":"Projects", "group": 1},
        {"id": "Node117", "label":"Projects", "group": 1},
        {"id": "Node118", "label":"Projects", "group": 1},
        {"id": "Node119", "label":"Projects", "group": 1},
        {"id": "Node120", "label":"Projects", "group": 1},
        {"id": "Node121", "label":"Projects", "group": 1},
        {"id": "Node122", "label":"Projects", "group": 1},
        {"id": "Node123", "label":"Projects", "group": 1},
        {"id": "Node124", "label":"Projects", "group": 1},
        {"id": "Node125", "label":"Projects", "group": 1},
        {"id": "Node126", "label":"Projects", "group": 1},
        {"id": "Node127", "label":"Projects", "group": 1},
        {"id": "Node128", "label":"Projects", "group": 1},
        {"id": "Node129", "label":"Projects", "group": 1},
        {"id": "Node130", "label":"Projects", "group": 1},
        {"id": "Node131", "label":"Projects", "group": 1},
        {"id": "Node132", "label":"Projects", "group": 1},
        {"id": "Node133", "label":"Projects", "group": 1},
        {"id": "Node134", "label":"Projects", "group": 1}, 
        {"id": "Node135", "label":"Projects", "group": 1},
        {"id": "Node136", "label":"Projects", "group": 1},
        {"id": "Node137", "label":"Projects", "group": 1},
        {"id": "Node138", "label":"Projects", "group": 1},
        {"id": "Node139", "label":"Projects", "group": 1},
        {"id": "Node140", "label":"Projects", "group": 1},
        {"id": "Node141", "label":"Projects", "group": 1},
        {"id": "Node142", "label":"Projects", "group": 1},
        {"id": "Node143", "label":"Projects", "group": 1},
        {"id": "Node144", "label":"Projects", "group": 1},
        {"id": "Node145", "label":"Projects", "group": 1},
        {"id": "Node146", "label":"Projects", "group": 1},
        {"id": "Node147", "label":"Projects", "group": 1},
        {"id": "Node148", "label":"Projects", "group": 1},
        {"id": "Node149", "label":"Projects", "group": 1},
        {"id": "Node150", "label":"Projects", "group": 1},
        {"id": "Node151", "label":"Projects", "group": 1},
        {"id": "Node152", "label":"Projects", "group": 1},
        {"id": "Node153", "label":"Projects", "group": 1},
        {"id": "Node154", "label":"Projects", "group": 1},
        {"id": "Node155", "label":"Projects", "group": 1},
        {"id": "Node156", "label":"Projects", "group": 1},
        {"id": "Node157", "label":"Projects", "group": 1},
        {"id": "Node158", "label":"Projects", "group": 1},
        {"id": "Node159", "label":"Projects", "group": 1},
        {"id": "Node160", "label":"Projects", "group": 1},
        {"id": "Node161", "label":"Projects", "group": 1}, 
        {"id": "Node162", "label":"Projects", "group": 1},
        {"id": "Node163", "label":"Projects", "group": 1},
        {"id": "Node164", "label":"Projects", "group": 1},
        {"id": "Node165", "label":"Projects", "group": 1},
        {"id": "Node166", "label":"Projects", "group": 1},
        {"id": "Node167", "label":"Projects", "group": 1},
        {"id": "Node168", "label":"Projects", "group": 1},
        {"id": "Node169", "label":"Projects", "group": 1},
        {"id": "Node170", "label":"Projects", "group": 1},
        {"id": "Node171", "label":"Projects", "group": 1},
        {"id": "Node172", "label":"Projects", "group": 1},
        {"id": "Node173", "label":"Projects", "group": 1},
        {"id": "Node174", "label":"Projects", "group": 1},
        {"id": "Node175", "label":"Projects", "group": 1},
        {"id": "Node176", "label":"Projects", "group": 1},
        {"id": "Node177", "label":"Projects", "group": 1},
        {"id": "Node178", "label":"Projects", "group": 1},
        {"id": "Node179", "label":"Projects", "group": 1},
        {"id": "Node180", "label":"Projects", "group": 1},
        {"id": "Node181", "label":"Projects", "group": 1},
        {"id": "Node182", "label":"Projects", "group": 1},
        {"id": "Node183", "label":"Projects", "group": 1},
        {"id": "Node184", "label":"Projects", "group": 1},
        {"id": "Node185", "label":"Projects", "group": 1},
        {"id": "Node186", "label":"Projects", "group": 1},
        {"id": "Node187", "label":"Projects", "group": 1},
        {"id": "Node188", "label":"Projects", "group": 1}, 
        {"id": "Node189", "label":"Projects", "group": 1},
        {"id": "Node190", "label":"Projects", "group": 1},
        {"id": "Node191", "label":"Projects", "group": 1},
        {"id": "Node192", "label":"Projects", "group": 1},
        {"id": "Node193", "label":"Projects", "group": 1},
        {"id": "Node194", "label":"Projects", "group": 1},
        {"id": "Node195", "label":"Projects", "group": 1},
        {"id": "Node196", "label":"Projects", "group": 1},
        {"id": "Node197", "label":"Projects", "group": 1},
        {"id": "Node198", "label":"Projects", "group": 1},
        {"id": "Node199", "label":"Projects", "group": 1},
        {"id": "Node200", "label":"Projects", "group": 1},
        {"id": "Node201", "label":"Projects", "group": 1},
        {"id": "Node202", "label":"Projects", "group": 1},
        {"id": "Node203", "label":"Projects", "group": 1},
        {"id": "Node204", "label":"Projects", "group": 1},
        {"id": "Node205", "label":"Projects", "group": 1},
        {"id": "Node206", "label":"Projects", "group": 1},
        {"id": "Node207", "label":"Projects", "group": 1},
        {"id": "Node208", "label":"Projects", "group": 1},
        {"id": "Node209", "label":"Projects", "group": 1},
        {"id": "Node210", "label":"Projects", "group": 1},
        {"id": "Node211", "label":"Projects", "group": 1},
        {"id": "Node212", "label":"Projects", "group": 1},
        {"id": "Node213", "label":"Projects", "group": 1},
        {"id": "Node214", "label":"Projects", "group": 1},
        {"id": "Node215", "label":"Projects", "group": 1}, 
        {"id": "Node216", "label":"Projects", "group": 1},
        {"id": "Node217", "label":"Projects", "group": 1},
        {"id": "Node218", "label":"Projects", "group": 1},
        {"id": "Node219", "label":"Projects", "group": 1},
        {"id": "Node220", "label":"Projects", "group": 1},
        {"id": "Node221", "label":"Projects", "group": 1},
        {"id": "Node222", "label":"Projects", "group": 1},
        {"id": "Node223", "label":"Projects", "group": 1},
        {"id": "Node224", "label":"Projects", "group": 1},
        {"id": "Node225", "label":"Projects", "group": 1},
        {"id": "Node226", "label":"Projects", "group": 1},
        {"id": "Node227", "label":"Projects", "group": 1},
        {"id": "Node228", "label":"Projects", "group": 1},
        {"id": "Node229", "label":"Projects", "group": 1},
        {"id": "Node230", "label":"Projects", "group": 1},
        {"id": "Node231", "label":"Projects", "group": 1},
        {"id": "Node232", "label":"Projects", "group": 1},
        {"id": "Node233", "label":"Projects", "group": 1},
        {"id": "Node234", "label":"Projects", "group": 1},
        {"id": "Node235", "label":"Projects", "group": 1},
        {"id": "Node236", "label":"Projects", "group": 1},
        {"id": "Node237", "label":"Projects", "group": 1},
        {"id": "Node238", "label":"Projects", "group": 1},
        {"id": "Node239", "label":"Projects", "group": 1},
        {"id": "Node240", "label":"Projects", "group": 1},
        {"id": "Node241", "label":"Projects", "group": 1},
        {"id": "Node242", "label":"Projects", "group": 1}, 
        {"id": "Node243", "label":"Projects", "group": 1},
        {"id": "Node244", "label":"Projects", "group": 1},
        {"id": "Node245", "label":"Projects", "group": 1},
        {"id": "Node246", "label":"Projects", "group": 1},
        {"id": "Node247", "label":"Projects", "group": 1},
        {"id": "Node248", "label":"Projects", "group": 1},
        {"id": "Node249", "label":"Projects", "group": 1},
        {"id": "Node250", "label":"Projects", "group": 1},
        {"id": "Node251", "label":"Projects", "group": 1},
        {"id": "Node252", "label":"Projects", "group": 1},
        {"id": "Node253", "label":"Projects", "group": 1},
        {"id": "Node254", "label":"Projects", "group": 1},
        {"id": "Node255", "label":"Projects", "group": 1},
        {"id": "Node256", "label":"Projects", "group": 1},
        {"id": "Node257", "label":"Projects", "group": 1},
        {"id": "Node258", "label":"Projects", "group": 1},
        {"id": "Node259", "label":"Projects", "group": 1},
        {"id": "Node260", "label":"Projects", "group": 1},
        {"id": "Node261", "label":"Projects", "group": 1},
        {"id": "Node262", "label":"Projects", "group": 1},
        {"id": "Node263", "label":"Projects", "group": 1},
        {"id": "Node264", "label":"Projects", "group": 1},
        {"id": "Node265", "label":"Projects", "group": 1},
        {"id": "Node266", "label":"Projects", "group": 1},
        {"id": "Node267", "label":"Projects", "group": 1},
        {"id": "Node268", "label":"Projects", "group": 1},
        {"id": "Node269", "label":"Projects", "group": 1}, 
        {"id": "Node270", "label":"Projects", "group": 1},
        {"id": "Node271", "label":"Projects", "group": 1},
        {"id": "Node272", "label":"Projects", "group": 1},
        {"id": "Node273", "label":"Projects", "group": 1},
        {"id": "Node274", "label":"Projects", "group": 1},
        {"id": "Node275", "label":"Projects", "group": 1},
        {"id": "Node276", "label":"Projects", "group": 1},
        {"id": "Node277", "label":"Projects", "group": 1},
        {"id": "Node278", "label":"Projects", "group": 1},
        {"id": "Node279", "label":"Projects", "group": 1},
        {"id": "Node280", "label":"Projects", "group": 1},
        {"id": "Node281", "label":"Projects", "group": 1},
        {"id": "Node282", "label":"Projects", "group": 1},
        {"id": "Node283", "label":"Projects", "group": 1},
        {"id": "Node284", "label":"Projects", "group": 1},
        {"id": "Node285", "label":"Projects", "group": 1},
        {"id": "Node286", "label":"Projects", "group": 1},
        {"id": "Node287", "label":"Projects", "group": 1},
        {"id": "Node288", "label":"Projects", "group": 1},
        {"id": "Node289", "label":"Projects", "group": 1},
        {"id": "Node290", "label":"Projects", "group": 1},
        {"id": "Node291", "label":"Projects", "group": 1},
        {"id": "Node292", "label":"Projects", "group": 1},
        {"id": "Node293", "label":"Projects", "group": 1},
        {"id": "Node294", "label":"Projects", "group": 1},
        {"id": "Node295", "label":"Projects", "group": 1},
        {"id": "Node296", "label":"Projects", "group": 1}, 
        {"id": "Node297", "label":"Projects", "group": 1},
        {"id": "Node298", "label":"Projects", "group": 1},
        {"id": "Node299", "label":"Projects", "group": 1},
        {"id": "Node300", "label":"Projects", "group": 1},
        {"id": "Node301", "label":"Projects", "group": 1},
        {"id": "Node302", "label":"Projects", "group": 1},
        {"id": "Node303", "label":"Projects", "group": 1},
        {"id": "Node304", "label":"Projects", "group": 1},
        {"id": "Node305", "label":"Projects", "group": 1},
        {"id": "Node306", "label":"Projects", "group": 1},
        {"id": "Node307", "label":"Projects", "group": 1},
        {"id": "Node308", "label":"Projects", "group": 1},
        {"id": "Node309", "label":"Projects", "group": 1},
        {"id": "Node310", "label":"Projects", "group": 1},
        {"id": "Node311", "label":"Projects", "group": 1},
        {"id": "Node312", "label":"Projects", "group": 1},
        {"id": "Node313", "label":"Projects", "group": 1},
        {"id": "Node314", "label":"Projects", "group": 1},
        {"id": "Node315", "label":"Projects", "group": 1},
        {"id": "Node316", "label":"Projects", "group": 1},
        {"id": "Node317", "label":"Projects", "group": 1},
        {"id": "Node318", "label":"Projects", "group": 1},
        {"id": "Node319", "label":"Projects", "group": 1},
        {"id": "Node320", "label":"Projects", "group": 1},
        {"id": "Node321", "label":"Projects", "group": 1},
        {"id": "Node322", "label":"Projects", "group": 1},
        {"id": "Node323", "label":"Projects", "group": 1}
    ],
    "links": [
    ]
}